{"chunk_definitions":[{"chunk_id":"ci1t5s1lcneig","chunk_label":"unnamed-chunk-1","document_id":"B729597B","expansion_state":0,"options":{"engine":"r","label":"unnamed-chunk-1"},"row":99,"row_count":1,"visible":true},{"chunk_id":"c6faot5o7nr09","chunk_label":"unnamed-chunk-2","document_id":"B729597B","expansion_state":0,"options":{"engine":"r","label":"unnamed-chunk-2"},"row":156,"row_count":1,"visible":true},{"chunk_id":"cscgbaxh6equq","chunk_label":"unnamed-chunk-3","document_id":"B729597B","expansion_state":0,"options":{"engine":"r","label":"unnamed-chunk-3"},"row":189,"row_count":1,"visible":true},{"chunk_id":"c7mr2kqs2n1pa","chunk_label":"unnamed-chunk-4","document_id":"B729597B","expansion_state":0,"options":{"engine":"r","label":"unnamed-chunk-4"},"row":336,"row_count":1,"visible":true},{"chunk_id":"cg5objyii5prs","chunk_label":"unnamed-chunk-5","document_id":"B729597B","expansion_state":0,"options":{"engine":"r","label":"unnamed-chunk-5"},"row":366,"row_count":1,"visible":true},{"chunk_id":"ct4j8mlgkx3al","chunk_label":"unnamed-chunk-6","document_id":"B729597B","expansion_state":0,"options":{"engine":"r","label":"unnamed-chunk-6"},"row":376,"row_count":1,"visible":true},{"chunk_id":"cpgevrtomopa9","chunk_label":"unnamed-chunk-8","document_id":"B729597B","expansion_state":0,"options":{"engine":"r","label":"unnamed-chunk-7"},"row":629,"row_count":1,"visible":true},{"chunk_id":"c1uhyz11w8ggb","chunk_label":"unnamed-chunk-9","document_id":"B729597B","expansion_state":0,"options":{"engine":"r","label":"unnamed-chunk-8"},"row":657,"row_count":1,"visible":true},{"chunk_id":"c2pphktvjx3p1","chunk_label":"unnamed-chunk-10","document_id":"B729597B","expansion_state":0,"options":{"engine":"r","label":"unnamed-chunk-9"},"row":768,"row_count":1,"visible":true},{"chunk_id":"cmgarsgxde4mr","chunk_label":"unnamed-chunk-11","document_id":"B729597B","expansion_state":0,"options":{"engine":"r","label":"unnamed-chunk-10"},"row":796,"row_count":1,"visible":true},{"chunk_id":"coa8lhp7b2e7o","chunk_label":"unnamed-chunk-12","document_id":"B729597B","expansion_state":0,"options":{"engine":"r","label":"unnamed-chunk-11"},"row":822,"row_count":1,"visible":true},{"chunk_id":"cut0cxemlt07i","chunk_label":"unnamed-chunk-13","document_id":"B729597B","expansion_state":0,"options":{"engine":"r","label":"unnamed-chunk-18"},"row":878,"row_count":1,"visible":true},{"chunk_id":"c7pddb6lneiui","chunk_label":"unnamed-chunk-14","document_id":"B729597B","expansion_state":0,"options":{"engine":"r","label":"unnamed-chunk-15"},"row":898,"row_count":1,"visible":true},{"chunk_id":"cx8l0csw8ihvi","chunk_label":"unnamed-chunk-15","document_id":"B729597B","expansion_state":0,"options":{"engine":"r","label":"unnamed-chunk-19"},"row":935,"row_count":1,"visible":true},{"chunk_id":"c50g4jqbd3ejj","chunk_label":"unnamed-chunk-16","document_id":"B729597B","expansion_state":0,"options":{"engine":"r","label":"unnamed-chunk-17"},"row":997,"row_count":1,"visible":true}],"chunk_rendered_width":683,"doc_write_time":1579192523}